hackday_bot/__init__.py
hackday_bot/bot.py
hackday_bot/cli.py
hackday_bot/const.py
hackday_bot/members.py
hackday_bot/util.py
hackday_bot-0.3.0.dist-info/DESCRIPTION.rst
hackday_bot-0.3.0.dist-info/METADATA
hackday_bot-0.3.0.dist-info/RECORD
hackday_bot-0.3.0.dist-info/WHEEL
hackday_bot-0.3.0.dist-info/entry_points.txt
hackday_bot-0.3.0.dist-info/metadata.json
hackday_bot-0.3.0.dist-info/top_level.txt
