Metadata-Version: 2.0
Name: hackday-bot
Version: 0.3.0
Summary: A Reddit bot that helps facilitate the creation and selection of ideas for a hack day.
Home-page: https://github.com/bboe/hackday_bot
Author: Bryce Boe
Author-email: bbzbryce@gmail.com
License: Simplified BSD License
Keywords: reddit bot hackday
Platform: UNKNOWN
Classifier: Development Status :: 4 - Beta
Classifier: Intended Audience :: Developers
Classifier: License :: OSI Approved :: BSD License
Classifier: Natural Language :: English
Classifier: Programming Language :: Python
Classifier: Programming Language :: Python :: 2.7
Classifier: Programming Language :: Python :: 3
Classifier: Programming Language :: Python :: 3.3
Classifier: Programming Language :: Python :: 3.4
Classifier: Programming Language :: Python :: 3.5
Classifier: Programming Language :: Python :: Implementation :: CPython
Requires-Dist: docopt (<1,>=0.6.2)
Requires-Dist: praw (>=5.0.0)
